internet_words_remover/__init__.py
internet_words_remover/_version.py
internet_words_remover/internet_words_remover.py
internet_words_remover/version.py
internet_words_remover-3.1.3.dist-info/LICENSE
internet_words_remover-3.1.3.dist-info/METADATA
internet_words_remover-3.1.3.dist-info/WHEEL
internet_words_remover-3.1.3.dist-info/entry_points.txt
internet_words_remover-3.1.3.dist-info/top_level.txt
internet_words_remover-3.1.3.dist-info/RECORD
