Metadata-Version: 2.1
Name: internet_words_remover
Version: 3.1.3
Summary: This module is helful for removing daily use chatting and business words from any string.
Author: Qadeer Ahmad
Author-email: <mrqadeer1231122@gmail.com>
Keywords: python,internet words,chatting words,words remover,nlp,textual data
Classifier: Development Status :: 1 - Planning
Classifier: Intended Audience :: Developers
Classifier: Programming Language :: Python :: 3
Classifier: Operating System :: Unix
Classifier: Operating System :: MacOS :: MacOS X
Classifier: Operating System :: Microsoft :: Windows
License-File: LICENSE
